.gitignore
.travis.yml
LICENSE
MANIFEST.in
README.rst
conftest.py
pytest.ini
setup.py
latlon_utils/__init__.py
latlon_utils/download.py
latlon_utils.egg-info/PKG-INFO
latlon_utils.egg-info/SOURCES.txt
latlon_utils.egg-info/dependency_links.txt
latlon_utils.egg-info/not-zip-safe
latlon_utils.egg-info/requires.txt
latlon_utils.egg-info/top_level.txt