Metadata-Version: 2.1
Name: latlon-utils
Version: 0.0.7
Summary: Retrieve WorldClim climate and other information for lat-lon grid cells
Home-page: https://github.com/Chilipp/latlon-utils
Author: Philipp S. Sommer
Author-email: philipp.sommer@hereon.de
License: GPLv3
Keywords: worldclim geo-countries latitude longitude
Platform: UNKNOWN
Classifier: Development Status :: 5 - Production/Stable
Classifier: Intended Audience :: Developers
Classifier: Topic :: Scientific/Engineering :: GIS
Classifier: Topic :: Scientific/Engineering
Classifier: License :: OSI Approved :: GNU General Public License v3 (GPLv3)
Classifier: Programming Language :: Python :: 3.5
Classifier: Programming Language :: Python :: 3.6
Classifier: Programming Language :: Python :: 3.7
Classifier: Programming Language :: Python :: 3.8
Classifier: Programming Language :: Python :: 3.9
Classifier: Programming Language :: Python :: 3.10
Classifier: Operating System :: OS Independent
